lorepy/__init__.py
lorepy/lorepy.py
lorepy/uncertainty.py
lorepy-0.4.4.dist-info/LICENSE
lorepy-0.4.4.dist-info/METADATA
lorepy-0.4.4.dist-info/WHEEL
lorepy-0.4.4.dist-info/top_level.txt
lorepy-0.4.4.dist-info/RECORD
