Metadata-Version: 2.1
Name: lorepy
Version: 0.4.4
Summary: Draw Logistic Regression Plots in Python
Home-page: https://github.com/raeslab/lorepy/
Author: Sebastian Proost
Author-email: sebastian.proost@gmail.com
License: Creative Commons Attribution-NonCommercial-ShareAlike 4.0. https://creativecommons.org/licenses/by-nc-sa/4.0/
Project-URL: Bug Tracker, https://github.com/raeslab/lorepy/issues
Classifier: Programming Language :: Python :: 3
Classifier: Operating System :: OS Independent
Requires-Python: >=3.9
License-File: LICENSE
Requires-Dist: matplotlib (>=3.4.1)
Requires-Dist: numpy (>=1.20.2)
Requires-Dist: pandas (>=1.2.4)
Requires-Dist: scikit-learn (>=1.5.0)
